unimortal/__init__.py
unimortal/fcmodel.py
unimortal/plots.py
unimortal/utils.py
unimortal/package_data/GLOBAL_DATAFLOW_infant_2009-2019.xlsx
unimortal/package_data/GLOBAL_DATAFLOW_under5_2009-2019.xlsx
unimortal/package_data/csv_infant_2009-2019.csv
unimortal/package_data/csv_under5_2009-2019.csv
unimortal/package_data/~$GLOBAL_DATAFLOW_infant_2009-2019.xlsx
unimortal-1.2.dist-info/METADATA
unimortal-1.2.dist-info/WHEEL
unimortal-1.2.dist-info/top_level.txt
unimortal-1.2.dist-info/RECORD
