Metadata-Version: 2.1
Name: unimortal
Version: 1.2
Summary: Tools to get inference from the Global Mortality Rate in Python
Home-page: UNKNOWN
Author: Gouri Birije, Katarzyna Jagoda, Hanieh Fasihy
Author-email: blahblah@gmail.com
License: UNKNOWN
Platform: UNKNOWN
Classifier: Programming Language :: Python :: 3.6
Classifier: Programming Language :: Python :: 3.7
Classifier: Programming Language :: Python :: 3.8
Classifier: Operating System :: OS Independent
Requires-Python: >=3.6.9
Requires-Dist: statsmodels (>=0.12.2)
Requires-Dist: matplotlib (>=3.1.3)
Requires-Dist: numpy (>=1.18.1)
Requires-Dist: pandas (>=1.0.1)
